README.md
guvva
setup.py
GUVVA.egg-info/PKG-INFO
GUVVA.egg-info/SOURCES.txt
GUVVA.egg-info/dependency_links.txt
GUVVA.egg-info/top_level.txt
guvva/__init__.py
guvva/code.py
guvva.egg-info/PKG-INFO
guvva.egg-info/SOURCES.txt
guvva.egg-info/dependency_links.txt
guvva.egg-info/top_level.txt