Metadata-Version: 2.1
Name: guvva
Version: 2.1.0
Summary: A tough programing language
Home-page: https://www.google.com
Author: MasterMind
Author-email: mastermindm2rd@gmail.com
License: UNKNOWN
Platform: UNKNOWN
Classifier: Programming Language :: Python :: 3
Classifier: License :: OSI Approved :: MIT License
Classifier: Operating System :: OS Independent
